insensitive_dict.py
insensitive_dict-1.0.0.dist-info/AUTHORS.rst
insensitive_dict-1.0.0.dist-info/LICENSE
insensitive_dict-1.0.0.dist-info/METADATA
insensitive_dict-1.0.0.dist-info/WHEEL
insensitive_dict-1.0.0.dist-info/top_level.txt
insensitive_dict-1.0.0.dist-info/RECORD
