Metadata-Version: 2.1
Name: insensitive-dict
Version: 1.0.0
Summary: A case insensitive dictionary that's fully tested.  Primarily broken out from the requests package
Home-page: https://github.com/timmmartin19/case_insensitive_dict
Author: Tim Martin
Author-email: tim@timmartin.me
License: MIT license
Keywords: case_insensitive_dict
Platform: UNKNOWN
Classifier: Development Status :: 2 - Pre-Alpha
Classifier: Intended Audience :: Developers
Classifier: License :: OSI Approved :: MIT License
Classifier: Natural Language :: English
Classifier: Programming Language :: Python :: 3
Classifier: Programming Language :: Python :: 3.5
Classifier: Programming Language :: Python :: 3.6
Classifier: Programming Language :: Python :: 3.7
Classifier: Programming Language :: Python :: 3.8
